{"name": "河川", "id": 136533, "predecessors": [{"name": "地形", "id": 145402}], "successors": [{"name": "廃河川", "id": 1347557}, {"name": "中州", "id": 1641485}, {"name": "河川の文化", "id": 1834616}, {"name": "同名の河川", "id": 2229147}, {"name": "河川水運", "id": 3253614}, {"name": "ライン川水系", "id": 523996}, {"name": "アムール川水系", "id": 528148}, {"name": "長江水系", "id": 1344526}, {"name": "多摩川水系", "id": 523928}, {"name": "利根川水系", "id": 523951}, {"name": "信濃川水系", "id": 524027}, {"name": "天竜川水系", "id": 524032}, {"name": "淀川水系", "id": 527199}, {"name": "富士川水系", "id": 533777}, {"name": "相模川水系", "id": 533786}, {"name": "木曽川水系", "id": 533876}, {"name": "阿武隈川水系", "id": 1076045}, {"name": "吉野川水系", "id": 1076065}, {"name": "阿賀野川水系", "id": 1076084}, {"name": "北上川水系", "id": 1107338}, {"name": "石狩川水系", "id": 1230787}, {"name": "那珂川水系", "id": 1249456}, {"name": "荒川水系_(関東)", "id": 1284766}, {"name": "神通川水系", "id": 1337679}, {"name": "九頭竜川水系", "id": 1338621}, {"name": "筑後川水系", "id": 1395432}, {"name": "最上川水系", "id": 1456391}]}