{"name": "キリスト教指導者", "id": 1521373, "predecessors": [{"name": "キリスト教の歴史", "id": 683407}, {"name": "主要カテゴリ", "id": 185451}, {"name": "旧約聖書の人物", "id": 201742}], "successors": [{"name": "名誉神学博士", "id": 2004728}, {"name": "キリスト教の称号・役職", "id": 1655490}, {"name": "キリスト教の修道女", "id": 3995549}, {"name": "正教会の主教", "id": 1638966}, {"name": "聖公会の主教", "id": 1961967}, {"name": "キリスト教功労者の受賞者", "id": 2860788}, {"name": "19世紀のキリスト教聖職者", "id": 4549527}, {"name": "20世紀のキリスト教聖職者", "id": 4549528}, {"name": "21世紀のキリスト教聖職者", "id": 4549530}, {"name": "19世紀のカトリック聖職者", "id": 4880472}, {"name": "20世紀のカトリック聖職者", "id": 4880473}, {"name": "21世紀のカトリック聖職者", "id": 4880474}]}