{"name": "ニューヨーク州の郡", "id": 195704, "predecessors": [{"name": "アメリカ合衆国の州", "id": 210964}], "successors": [{"name": "ウェストチェスター郡_(ニューヨーク州)", "id": 3114405}, {"name": "マンハッタンの地区", "id": 2694718}, {"name": "マンハッタンの建築物", "id": 2706198}, {"name": "ブロードウェイ", "id": 3291123}, {"name": "マンハッタン出身の人物", "id": 3431638}, {"name": "マンハッタンの歴史", "id": 4854716}, {"name": "ブロンクス出身の人物", "id": 1867371}, {"name": "ブルックリン出身の人物", "id": 3408271}, {"name": "ブルックリンを舞台とした映画作品", "id": 3605667}, {"name": "クイーンズ出身の人物", "id": 3431258}, {"name": "クイーンズのニューヨーク市地下鉄駅", "id": 3390696}, {"name": "ブロンクスのニューヨーク市地下鉄駅", "id": 3395480}, {"name": "ブルックリン・ドジャースの選手", "id": 3681248}, {"name": "バッファロー出身の人物", "id": 2420520}, {"name": "ニューヨーク州サフォーク郡出身の人物", "id": 3431582}, {"name": "ニューヨーク州オールバニ出身の人物", "id": 2935906}, {"name": "ニューヨーク州ロチェスター出身の人物", "id": 2936694}, {"name": "マディソン・スクエア・ガーデン", "id": 3290626}]}