{"name": "アメリカ合衆国の多国籍企業", "id": 3294136, "predecessors": [{"name": "アメリカ合衆国の企業", "id": 649562}, {"name": "国際組織", "id": 192664}], "successors": [{"name": "IBM", "id": 186896}, {"name": "ディズニー", "id": 398621}, {"name": "ゼネラル・エレクトリック", "id": 1656969}, {"name": "コカ・コーラ", "id": 1782051}, {"name": "Apple", "id": 2680600}, {"name": "ワーナー・ミュージック・グループのアーティスト", "id": 759405}, {"name": "ワーナーミュージック・ジャパンのアルバム", "id": 894635}, {"name": "エレクトラ・レコードのアルバム", "id": 1089151}, {"name": "アトランティック・レコードのアルバム", "id": 1862379}, {"name": "ワーナー・ブラザース・レコードのアルバム", "id": 1864134}, {"name": "RCAレコードのアルバム", "id": 1669487}, {"name": "アリスタ・レコードのアルバム", "id": 1669553}, {"name": "エピック・レコードのアルバム", "id": 1881337}, {"name": "コロムビア・レコードのアルバム", "id": 1881353}]}