{"name": "公共圏", "id": 3851662, "predecessors": [{"name": "社会", "id": 139645}], "successors": [{"name": "公衆浴場", "id": 347760}, {"name": "公衆衛生", "id": 349025}, {"name": "公企業", "id": 2647470}, {"name": "租税", "id": 226967}, {"name": "財政", "id": 280645}, {"name": "政治経済学", "id": 1832586}, {"name": "行政学者", "id": 2054384}, {"name": "脱中央集権", "id": 4044280}, {"name": "英国放送協会", "id": 519749}, {"name": "韓国放送公社", "id": 742987}, {"name": "国営放送", "id": 4525249}, {"name": "刑法", "id": 133371}, {"name": "国際法", "id": 200350}, {"name": "憲法", "id": 202463}, {"name": "日本の医療機関_(公益法人)", "id": 862925}, {"name": "解散した財団法人", "id": 2177835}, {"name": "解散した社団法人", "id": 2178726}, {"name": "プロパガンダ", "id": 1069422}, {"name": "パブリック・リレーションズ", "id": 1537699}, {"name": "経済政策", "id": 339951}, {"name": "安全保障", "id": 561925}, {"name": "エネルギー政策", "id": 665770}, {"name": "交通政策", "id": 730088}, {"name": "刑事政策学者", "id": 1140820}, {"name": "社会政策学者", "id": 3382264}, {"name": "帝国主義", "id": 1163356}, {"name": "宇宙開発", "id": 204608}, {"name": "都市計画", "id": 262340}, {"name": "能力開発", "id": 648413}, {"name": "国際開発", "id": 2706810}, {"name": "土地開発", "id": 3590423}, {"name": "裁判", "id": 280183}, {"name": "日本の行政作用法", "id": 2590582}, {"name": "建築関連法規", "id": 2423214}, {"name": "日本の行政組織法", "id": 2590602}, {"name": "公施設法人", "id": 2596124}, {"name": "治安", "id": 197804}, {"name": "教育問題", "id": 424682}, {"name": "日本の教育行政", "id": 269555}, {"name": "文部科学省", "id": 121425}, {"name": "文部省", "id": 3300296}, {"name": "日本の人権", "id": 2161038}, {"name": "日本の刑事手続法", "id": 2591177}, {"name": "日本の民事手続法", "id": 2645530}, {"name": "登記", "id": 729087}, {"name": "表現規制", "id": 451918}, {"name": "運転免許", "id": 359174}, {"name": "医師", "id": 503095}, {"name": "国家試験", "id": 841998}, {"name": "日本の国家資格", "id": 2180213}, {"name": "裁判官", "id": 368816}, {"name": "非政府組織", "id": 200573}, {"name": "政治活動家", "id": 927429}, {"name": "市民活動家", "id": 1040294}, {"name": "社会福祉活動家", "id": 4818626}, {"name": "社会運動", "id": 103827}, {"name": "反戦運動", "id": 158048}, {"name": "人権活動家", "id": 1193852}, {"name": "民主活動家", "id": 4143906}, {"name": "フリーソフトウェア文化・運動", "id": 1482322}, {"name": "カトリック百科事典", "id": 236721}, {"name": "環境マネジメント", "id": 183633}, {"name": "日本放送協会", "id": 225433}, {"name": "全国労働組合総連合", "id": 1308480}, {"name": "日本労働組合総連合会", "id": 1308483}, {"name": "日本教職員組合の人物", "id": 2207009}, {"name": "全日本自治団体労働組合の人物", "id": 4136317}, {"name": "国鉄労働組合の人物", "id": 4158377}, {"name": "日本の憲法学者", "id": 4643586}, {"name": "日本の国際法学者", "id": 4643593}, {"name": "日本の行政法学者", "id": 4650303}, {"name": "日本の経済法学者", "id": 4650311}, {"name": "放送に関する制度", "id": 409886}, {"name": "文化遺産保護制度", "id": 1408138}, {"name": "国家賠償請求訴訟", "id": 3276594}, {"name": "19世紀日本の活動家", "id": 4480688}, {"name": "20世紀日本の活動家", "id": 4480691}, {"name": "21世紀日本の活動家", "id": 4480720}]}