{"name": "人間のコミュニケーション", "id": 4520489, "predecessors": [{"name": "人間行動学", "id": 743134}, {"name": "人間関係", "id": 988775}], "successors": [{"name": "国際交流", "id": 285041}, {"name": "手話", "id": 420922}, {"name": "教育の手法", "id": 1032043}, {"name": "人間とコンピュータの相互作用", "id": 1179268}, {"name": "ユーモア", "id": 1419997}, {"name": "パブリック・リレーションズ", "id": 1537699}, {"name": "協働", "id": 1626475}, {"name": "音声", "id": 1936990}, {"name": "会合", "id": 1938737}, {"name": "オーラルコミュニケーション", "id": 1940494}, {"name": "社交ダンス", "id": 840715}, {"name": "マナー", "id": 1448679}, {"name": "日本の親睦団体", "id": 766255}, {"name": "ジェスチャー", "id": 1938735}, {"name": "認知バイアス", "id": 766723}, {"name": "広く信じられた謬説", "id": 3328723}, {"name": "ソーシャル・ネットワーキング・サービス", "id": 457952}, {"name": "クラウドソーシング", "id": 2049183}, {"name": "吃音の人物", "id": 2562622}]}